setup.py
test/test.py
uasparser2/__init__.py
uasparser2.egg-info/PKG-INFO
uasparser2.egg-info/SOURCES.txt
uasparser2.egg-info/dependency_links.txt
uasparser2.egg-info/top_level.txt
uasparser2.egg-info/zip-safe