Metadata-Version: 1.0
Name: uasparser2
Version: 0.2
Summary: Fast and reliable User Agent parser for Python.
Home-page: https://github.com/hamaxx/uasparser2
Author: Jure Ham
Author-email: jure.ham@zemanta.com
License: BSD
Platform: any
